CHANGES.rst
MANIFEST.in
README.rst
setup.py
docs/LICENSE.GPL
docs/LICENSE.txt
plone/__init__.py
plone.app.form.egg-info/PKG-INFO
plone.app.form.egg-info/SOURCES.txt
plone.app.form.egg-info/dependency_links.txt
plone.app.form.egg-info/namespace_packages.txt
plone.app.form.egg-info/not-zip-safe
plone.app.form.egg-info/requires.txt
plone.app.form.egg-info/top_level.txt
plone/app/__init__.py
plone/app/form/__init__.py
plone/app/form/_named.py
plone/app/form/_patches.py
plone/app/form/addingpageform.pt
plone/app/form/base.py
plone/app/form/configure.zcml
plone/app/form/events.py
plone/app/form/exception.py
plone/app/form/formlib.txt
plone/app/form/inline_validation.py
plone/app/form/inline_validation.txt
plone/app/form/interfaces.py
plone/app/form/overrides.zcml
plone/app/form/pageform.pt
plone/app/form/subpageform.pt
plone/app/form/testing.py
plone/app/form/validators.py
plone/app/form/tests/__init__.py
plone/app/form/tests/test_doctests.py
plone/app/form/tests/test_sequencewidget.py
plone/app/form/tests/test_widgets.py
plone/app/form/tests/test_wysiwygwidget.py
plone/app/form/widgets/__init__.py
plone/app/form/widgets/checkboxwidget.py
plone/app/form/widgets/checkboxwidget.txt
plone/app/form/widgets/configure.zcml
plone/app/form/widgets/fileupload.py
plone/app/form/widgets/interfaces.py
plone/app/form/widgets/multicheckboxwidget.py
plone/app/form/widgets/overrides.zcml
plone/app/form/widgets/selectionwidget.py
plone/app/form/widgets/sequencewidget.py
plone/app/form/widgets/ubermultiselectionwidget.pt
plone/app/form/widgets/uberselectionwidget.pt
plone/app/form/widgets/uberselectionwidget.py
plone/app/form/widgets/uberselectionwidget.txt
plone/app/form/widgets/wysiwygwidget.pt
plone/app/form/widgets/wysiwygwidget.py