Metadata-Version: 2.1
Name: plone.app.form
Version: 2.3.3
Summary: zope.formlib integration for Plone
Home-page: http://pypi.python.org/pypi/plone.app.form
Author: Plone Foundation
Author-email: plone-developers@lists.sourceforge.net
License: GPL version 2
Keywords: plone form formlib
Platform: UNKNOWN
Classifier: Environment :: Web Environment
Classifier: Framework :: Plone
Classifier: Framework :: Zope2
Classifier: License :: OSI Approved :: GNU General Public License (GPL)
Classifier: Operating System :: OS Independent
Classifier: Programming Language :: Python
Provides-Extra: test
